cloudutils/__init__.py
cloudutils/instance/__init__.py
cloudutils/instance/ec2.py
cloudutils/instance/gce.py
cloudutils/instance/instance.py
cloudutils/vault/__init__.py
cloudutils/vault/ec2.py
cloudutils/vault/eks.py
cloudutils/vault/gce.py
cloudutils/vault/vault.py
viant_cloudutils_python3-0.2.9.dist-info/METADATA
viant_cloudutils_python3-0.2.9.dist-info/WHEEL
viant_cloudutils_python3-0.2.9.dist-info/top_level.txt
viant_cloudutils_python3-0.2.9.dist-info/RECORD
