Metadata-Version: 2.1
Name: viant-cloudutils-python3
Version: 0.2.9
Summary: Cloud utilities for automation
Home-page: https://github.vianttech.com/techops/cloudutils
Author: Lee Sautia
Author-email: lsautia@viantinc.com
Classifier: Programming Language :: Python :: 3
Classifier: License :: OSI Approved :: MIT License
Classifier: Operating System :: OS Independent
Requires-Dist: requests ==2.24.0
Requires-Dist: botocore ==1.19.0
Requires-Dist: boto3 ==1.16.0
Requires-Dist: retry ==0.9.2
